zincbase/__init__.py
zincbase/zb.py
zincbase/graph/Edge.py
zincbase/graph/Node.py
zincbase/graph/__init__.py
zincbase/logic/Goal.py
zincbase/logic/Negative.py
zincbase/logic/Rule.py
zincbase/logic/Term.py
zincbase/logic/__init__.py
zincbase/logic/common.py
zincbase/nn/__init__.py
zincbase/nn/dataloader.py
zincbase/nn/rotate.py
zincbase/utils/__init__.py
zincbase/utils/calc_auc_roc.py
zincbase/utils/calc_mrr.py
zincbase/utils/string_utils.py
zincbase/utils/type_checks.py
zincbase/web/__init__.py
zincbase/web/__main__.py
zincbase/web/socket_server.py
zincbase/web/static/bundle.js
zincbase/web/static/index.html
zincbase-0.10.1.dist-info/LICENSE
zincbase-0.10.1.dist-info/METADATA
zincbase-0.10.1.dist-info/WHEEL
zincbase-0.10.1.dist-info/top_level.txt
zincbase-0.10.1.dist-info/RECORD
