Metadata-Version: 2.1
Name: zincbase
Version: 0.10.1
Summary: A state of the art knowledge base
Home-page: https://github.com/complexdb/zincbase
Author: ComplexDB
Author-email: tom@complexdb.com
License: MIT
Platform: UNKNOWN
Classifier: Programming Language :: Python :: 3
Classifier: License :: OSI Approved :: MIT License
Classifier: Operating System :: OS Independent
Requires-Python: >=3.6
Requires-Dist: matplotlib
Requires-Dist: networkx
Requires-Dist: numpy
Requires-Dist: scipy
Requires-Dist: sklearn
Requires-Dist: torch
Requires-Dist: torchvision
Requires-Dist: tqdm
Provides-Extra: web
Requires-Dist: flask-socketio ; extra == 'web'
Requires-Dist: redis ; extra == 'web'
Requires-Dist: eventlet ; extra == 'web'
